[
  {
    "locationName": "KARAIKAL",
    "area": {
      "non_recharge_worthy": {
        "commandArea": 0.0,
        "nonCommandArea": 0.0,
        "poorQualityArea": 0.0,
        "hillyArea": 0.0,
        "forestArea": 0.0,
        "totalArea": 0.0,
        "pavedArea": 0.0,
        "unpavedArea": 0.0
      },
      "total": {
        "commandArea": 0.0,
        "nonCommandArea": 9958.0,
        "poorQualityArea": 6142.0,
        "hillyArea": 0.0,
        "forestArea": 0.0,
        "totalArea": 16100.0,
        "pavedArea": 0.0,
        "unpavedArea": 0.0
      },
      "recharge_worthy": {
        "commandArea": 0.0,
        "nonCommandArea": 9958.0,
        "poorQualityArea": 6142.0,
        "hillyArea": 0.0,
        "forestArea": 0.0,
        "totalArea": 16100.0,
        "pavedArea": 0.0,
        "unpavedArea": 0.0
      }
    },
    "loss": {
      "poor_quality": 0.0,
      "total": 442.41999999999996,
      "non_command": 226.09000000000003,
      "command": 216.32
    },
    "category": {
      "poor_quality": "none",
      "total": "safe",
      "non_command": "semi_critical"
    },
    "reportSummary": {
      "total": {
        "TALUK": {
          "safe": 2
        },
        "REGION": {
          "safe": 1
        }
      },
      "6b78fa34-3173-4e8b-b545-fd82bb053da9": {
        "TALUK": {
          "safe": 2
        },
        "REGION": {
          "safe": 1
        }
      }
    },
    "gwProjectedUtilAllocationDynamicAquifer": {
      "domestic": {
        "total": 0.0
      },
      "total": {
        "total": 0.0
      }
    },
    "additionalRecharge": {},
    "staticGWResource": {
      "poor_quality": 0.0,
      "total": 0.0,
      "non_command": 0.0,
      "command": 0.0
    },
    "totalGWAvailability": {
      "poor_quality": 0.0,
      "total": 3981.6000000000004,
      "non_command": 2034.8200000000002,
      "command": 1946.78
    },
    "aquiferBusinessData": {
      "confined_aquifer": {
        "total": {
          "total": 0.0
        },
        "in_storage_gw": {
          "in_storage_gw": 0.0
        },
        "dynamic_gw": {
          "dynamic_gw": 0.0
        }
      }
    },
    "coastalBusinessData": null,
    "waterDepletedZonesBusinessData": null,
    "inOutFlow": {
      "total": 0.0
    },
    "baseFlow": {
      "total": {
        "lateral_aquifer": 0.0,
        "vertcal_aquifer": 0.0
      }
    },
    "streamRecharge": null,
    "additionalbaseflow": null,
    "envFlows": null,
    "subject": null,
    "action": null,
    "modifiable": null,
    "isUrban": null,
    "gwSpecificYield": null,
    "geology": null,
    "evaporation": {},
    "qualityTagging": null,
    "approvalLevel": 4,
    "verificStatus": 1,
    "timeStamp": null,
    "locationUUID": "f467febf-3708-45c8-b556-eac952bdbe3d",
    "rainfall": {
      "poor_quality": 0.0,
      "total": 779.940248447205,
      "non_command": 1261.0,
      "command": 0.0
    },
    "wtfonly": null,
    "computationSummary": {
      "annual": {
        "stage": {
          "poor_quality": {
            "av": "0.0"
          },
          "total": {
            "av": "3981.6"
          },
          "non_command": {
            "av": "2034.82"
          }
        }
      }
    },
    "rechargeData": {
      "agriculture": {
        "poor_quality": 0.0,
        "total": 0.0,
        "non_command": 0.0,
        "command": 0.0
      },
      "rainfall": {
        "poor_quality": 0.0,
        "total": 1421.84,
        "non_command": 1421.84,
        "command": 0.0
      },
      "total": {
        "poor_quality": 0.0,
        "total": 4424.01,
        "non_command": 2260.91,
        "command": 2163.1000000000004
      },
      "surface_irrigation": {
        "poor_quality": 0.0,
        "total": 0.0,
        "non_command": 0.0,
        "command": 0.0
      },
      "gw_irrigation": {
        "poor_quality": 0.0,
        "total": 0.0,
        "non_command": 0.0,
        "command": 0.0
      },
      "water_body": {
        "total": 419.07000000000005,
        "non_command": 419.07000000000005,
        "command": 0.0
      },
      "canal": {
        "total": 2163.1000000000004,
        "command": 2163.1000000000004
      },
      "artificial_structure": {
        "total": 420.0,
        "non_command": 420.0
      }
    },
    "draftData": {
      "agriculture": {
        "poor_quality": 0.0,
        "total": 528.78,
        "non_command": 528.78
      },
      "domestic": {
        "poor_quality": 0.0,
        "total": 946.8777074999999,
        "non_command": 946.8777074999999
      },
      "total": {
        "poor_quality": 0.0,
        "total": 1493.24,
        "non_command": 1493.24
      },
      "industry": {
        "poor_quality": 0.0,
        "total": 17.58,
        "non_command": 17.58
      }
    },
    "currentAvailabilityForAllPurposes": {
      "poor_quality": 0.0,
      "total": 3981.5999999999995,
      "non_command": 2034.82,
      "command": 1946.7800000000002
    },
    "availabilityForFutureUse": {
      "poor_quality": 0.0,
      "total": 2280.67,
      "non_command": 333.89,
      "command": 1946.78
    },
    "gwallocation": {
      "domestic": {
        "poor_quality": 0.0,
        "total": 1154.5700000000002,
        "non_command": 1154.5700000000002,
        "command": 0.0
      },
      "total": {
        "poor_quality": 0.0,
        "total": 1154.5700000000002,
        "non_command": 1154.5700000000002,
        "command": 0.0
      },
      "industry": {
        "poor_quality": 0.0,
        "total": 0.0
      }
    },
    "stageOfExtraction": {
      "poor_quality": -100000.0,
      "total": 37.50351617440226,
      "non_command": 73.38437797937901
    },
    "gwlevelData": null,
    "gwanalysisSeason": null,
    "gwtrendSlope": null,
    "waterTableRiseFall": null,
    "gwtrendAttention": null,
    "waterTableCategory": null,
    "message": null
  },
  {
    "locationName": "PUDUCHERRY",
    "area": {
      "non_recharge_worthy": {
        "commandArea": 0.0,
        "nonCommandArea": 0.0,
        "poorQualityArea": 0.0,
        "hillyArea": 0.0,
        "forestArea": 0.0,
        "totalArea": 0.0,
        "pavedArea": 0.0,
        "unpavedArea": 0.0
      },
      "total": {
        "commandArea": 0.0,
        "nonCommandArea": 30200.0,
        "poorQualityArea": 2000.0,
        "hillyArea": 0.0,
        "forestArea": 0.0,
        "totalArea": 32200.0,
        "pavedArea": 0.0,
        "unpavedArea": 0.0
      },
      "recharge_worthy": {
        "commandArea": 0.0,
        "nonCommandArea": 30200.0,
        "poorQualityArea": 2000.0,
        "hillyArea": 0.0,
        "forestArea": 0.0,
        "totalArea": 32200.0,
        "pavedArea": 0.0,
        "unpavedArea": 0.0
      }
    },
    "loss": {
      "poor_quality": 0.0,
      "total": 1213.73,
      "non_command": 1201.49,
      "command": 12.24
    },
    "category": {
      "poor_quality": "none",
      "total": "semi_critical",
      "non_command": "semi_critical"
    },
    "reportSummary": {
      "0b3a8ce7-4fd5-48df-a1d7-1022740adc1f": {
        "TALUK": {
          "over_exploited": 1,
          "semi_critical": 3
        },
        "REGION": {
          "semi_critical": 1
        }
      },
      "total": {
        "TALUK": {
          "salinity": 1,
          "over_exploited": 1,
          "semi_critical": 3,
          "safe": 1
        },
        "REGION": {
          "salinity": 1,
          "semi_critical": 1,
          "safe": 1
        }
      },
      "08451331-2701-49d7-9e32-6f4c79dfc7f0": {
        "TALUK": {
          "salinity": 1
        },
        "REGION": {
          "salinity": 1
        }
      },
      "de69e7f3-4897-45a2-885d-525ddc03dd20": {
        "TALUK": {
          "safe": 1
        },
        "REGION": {
          "safe": 1
        }
      }
    },
    "gwProjectedUtilAllocationDynamicAquifer": {
      "domestic": {
        "total": 0.0
      },
      "total": {
        "total": 0.0
      }
    },
    "additionalRecharge": {},
    "staticGWResource": {
      "poor_quality": 0.0,
      "total": 0.0,
      "non_command": 0.0,
      "command": 0.0
    },
    "totalGWAvailability": {
      "poor_quality": 0.0,
      "total": 13458.02,
      "non_command": 13347.970000000001,
      "command": 110.05000000000001
    },
    "aquiferBusinessData": {
      "confined_aquifer": {
        "total": {
          "total": 0.0
        },
        "in_storage_gw": {
          "in_storage_gw": 0.0
        },
        "dynamic_gw": {
          "dynamic_gw": 0.0
        }
      }
    },
    "coastalBusinessData": null,
    "waterDepletedZonesBusinessData": null,
    "inOutFlow": {
      "total": 0.0
    },
    "baseFlow": {
      "total": {
        "lateral_aquifer": 0.0,
        "vertcal_aquifer": 0.0
      }
    },
    "streamRecharge": null,
    "additionalbaseflow": null,
    "envFlows": null,
    "subject": null,
    "action": null,
    "modifiable": null,
    "isUrban": null,
    "gwSpecificYield": null,
    "geology": null,
    "evaporation": {},
    "qualityTagging": null,
    "approvalLevel": 4,
    "verificStatus": 1,
    "timeStamp": null,
    "locationUUID": "b8e6f4c8-046d-4f3a-9fb0-403c8081f66d",
    "rainfall": {
      "poor_quality": 0.0,
      "total": 1481.1211180124224,
      "non_command": 1579.208609271523,
      "command": 0.0
    },
    "wtfonly": null,
    "computationSummary": {
      "annual": {
        "stage": {
          "poor_quality": {
            "av": "0.0"
          },
          "total": {
            "av": "13458.02"
          },
          "non_command": {
            "av": "13347.97"
          }
        }
      }
    },
    "rechargeData": {
      "agriculture": {
        "poor_quality": 0.0,
        "total": 6199.639999999999,
        "non_command": 6199.639999999999,
        "command": 0.0
      },
      "rainfall": {
        "poor_quality": 0.0,
        "total": 5161.2,
        "non_command": 5161.2,
        "command": 0.0
      },
      "total": {
        "poor_quality": 0.0,
        "total": 14671.750000000002,
        "non_command": 14549.46,
        "command": 122.28999999999999
      },
      "surface_irrigation": {
        "poor_quality": 0.0,
        "total": 0.0,
        "non_command": 0.0,
        "command": 0.0
      },
      "gw_irrigation": {
        "poor_quality": 0.0,
        "total": 6199.639999999999,
        "non_command": 6199.639999999999,
        "command": 0.0
      },
      "water_body": {
        "poor_quality": 0.0,
        "total": 2278.62,
        "non_command": 2278.62,
        "command": 0.0
      },
      "canal": {
        "total": 122.28999999999999,
        "command": 122.28999999999999
      },
      "artificial_structure": {
        "poor_quality": 0.0,
        "total": 910.0,
        "non_command": 910.0,
        "command": 0.0
      }
    },
    "draftData": {
      "agriculture": {
        "poor_quality": 0.0,
        "total": 6888.5,
        "non_command": 6888.5
      },
      "domestic": {
        "poor_quality": 0.0,
        "total": 4322.423805,
        "non_command": 4322.423805
      },
      "total": {
        "poor_quality": 0.0,
        "total": 11758.13,
        "non_command": 11758.13
      },
      "industry": {
        "poor_quality": 0.0,
        "total": 547.2,
        "non_command": 547.2
      }
    },
    "currentAvailabilityForAllPurposes": {
      "poor_quality": 0.0,
      "total": 13458.02,
      "non_command": 13347.970000000001,
      "command": 110.05000000000001
    },
    "availabilityForFutureUse": {
      "poor_quality": 0.0,
      "total": 1158.92,
      "non_command": 1048.8700000000001,
      "command": 110.05000000000001
    },
    "gwallocation": {
      "domestic": {
        "poor_quality": 0.0,
        "total": 5498.94,
        "non_command": 5498.94,
        "command": 0.0
      },
      "total": {
        "poor_quality": 0.0,
        "total": 5498.94,
        "non_command": 5498.94,
        "command": 0.0
      },
      "industry": {
        "poor_quality": 0.0,
        "total": 0.0
      }
    },
    "stageOfExtraction": {
      "poor_quality": -100000.0,
      "total": 87.36894431721754,
      "non_command": 88.08927499837053
    },
    "gwlevelData": null,
    "gwanalysisSeason": null,
    "gwtrendSlope": null,
    "waterTableRiseFall": null,
    "gwtrendAttention": null,
    "waterTableCategory": null,
    "message": null
  },
  {
    "locationName": "total",
    "area": {
      "non_recharge_worthy": {
        "commandArea": 0.0,
        "nonCommandArea": 0.0,
        "poorQualityArea": 0.0,
        "hillyArea": 0.0,
        "forestArea": 0.0,
        "totalArea": 0.0,
        "pavedArea": 0.0,
        "unpavedArea": 0.0
      },
      "total": {
        "commandArea": 0.0,
        "nonCommandArea": 40158.0,
        "poorQualityArea": 8142.0,
        "hillyArea": 0.0,
        "forestArea": 0.0,
        "totalArea": 48300.0,
        "pavedArea": 0.0,
        "unpavedArea": 0.0
      },
      "recharge_worthy": {
        "commandArea": 0.0,
        "nonCommandArea": 40158.0,
        "poorQualityArea": 8142.0,
        "hillyArea": 0.0,
        "forestArea": 0.0,
        "totalArea": 48300.0,
        "pavedArea": 0.0,
        "unpavedArea": 0.0
      }
    },
    "loss": {
      "poor_quality": 0.0,
      "total": 1656.15,
      "non_command": 1427.58,
      "command": 228.56
    },
    "category": null,
    "reportSummary": {
      "total": {
        "TALUK": {
          "over_exploited": 1,
          "salinity": 1,
          "semi_critical": 3,
          "safe": 3
        },
        "REGION": {
          "salinity": 1,
          "semi_critical": 1,
          "safe": 2
        }
      },
      "b8e6f4c8-046d-4f3a-9fb0-403c8081f66d": {
        "TALUK": {
          "over_exploited": 1,
          "salinity": 1,
          "semi_critical": 3,
          "safe": 1
        },
        "REGION": {
          "salinity": 1,
          "semi_critical": 1,
          "safe": 1
        }
      },
      "f467febf-3708-45c8-b556-eac952bdbe3d": {
        "TALUK": {
          "safe": 2
        },
        "REGION": {
          "safe": 1
        }
      }
    },
    "gwProjectedUtilAllocationDynamicAquifer": {
      "domestic": {
        "total": 0.0
      },
      "total": {
        "total": 0.0
      }
    },
    "additionalRecharge": {},
    "staticGWResource": {
      "poor_quality": 0.0,
      "total": 0.0,
      "non_command": 0.0,
      "command": 0.0
    },
    "totalGWAvailability": {
      "poor_quality": 0.0,
      "total": 17439.620000000003,
      "non_command": 15382.79,
      "command": 2056.83
    },
    "aquiferBusinessData": {
      "SemiConfined Aquifer Piezo Data": null,
      "confined_aquifer": {
        "total": {
          "total": 0.0
        },
        "in_storage_gw": {
          "in_storage_gw": 0.0
        },
        "dynamic_gw": {
          "dynamic_gw": 0.0
        }
      }
    },
    "coastalBusinessData": null,
    "waterDepletedZonesBusinessData": null,
    "inOutFlow": {
      "total": 0.0
    },
    "baseFlow": {
      "total": {
        "lateral_aquifer": 0.0,
        "vertcal_aquifer": 0.0
      }
    },
    "streamRecharge": null,
    "additionalbaseflow": null,
    "envFlows": null,
    "subject": null,
    "action": null,
    "modifiable": null,
    "isUrban": null,
    "gwSpecificYield": null,
    "geology": null,
    "evaporation": {},
    "qualityTagging": null,
    "approvalLevel": null,
    "verificStatus": null,
    "timeStamp": null,
    "locationUUID": null,
    "rainfall": {
      "poor_quality": 0.0,
      "total": 1247.3941614906832,
      "non_command": 1500.3022560884506,
      "command": 0.0
    },
    "wtfonly": null,
    "computationSummary": null,
    "rechargeData": {
      "agriculture": {
        "poor_quality": 0.0,
        "total": 6199.639999999999,
        "non_command": 6199.639999999999,
        "command": 0.0
      },
      "rainfall": {
        "poor_quality": 0.0,
        "total": 6583.04,
        "non_command": 6583.04,
        "command": 0.0
      },
      "total": {
        "poor_quality": 0.0,
        "total": 19095.760000000002,
        "non_command": 16810.37,
        "command": 2285.3900000000003
      },
      "surface_irrigation": {
        "poor_quality": 0.0,
        "total": 0.0,
        "non_command": 0.0,
        "command": 0.0
      },
      "gw_irrigation": {
        "poor_quality": 0.0,
        "total": 6199.639999999999,
        "non_command": 6199.639999999999,
        "command": 0.0
      },
      "water_body": {
        "poor_quality": 0.0,
        "total": 2697.69,
        "non_command": 2697.69,
        "command": 0.0
      },
      "canal": {
        "total": 2285.3900000000003,
        "command": 2285.3900000000003
      },
      "artificial_structure": {
        "poor_quality": 0.0,
        "total": 1330.0,
        "non_command": 1330.0,
        "command": 0.0
      }
    },
    "draftData": {
      "agriculture": {
        "poor_quality": 0.0,
        "total": 7417.28,
        "non_command": 7417.28
      },
      "domestic": {
        "poor_quality": 0.0,
        "total": 5269.3015125,
        "non_command": 5269.3015125
      },
      "total": {
        "poor_quality": 0.0,
        "total": 13251.369999999999,
        "non_command": 13251.369999999999
      },
      "industry": {
        "poor_quality": 0.0,
        "total": 564.7800000000001,
        "non_command": 564.7800000000001
      }
    },
    "currentAvailabilityForAllPurposes": {
      "poor_quality": 0.0,
      "total": 17439.62,
      "non_command": 15382.79,
      "command": 2056.8300000000004
    },
    "availabilityForFutureUse": {
      "poor_quality": 0.0,
      "total": 3439.59,
      "non_command": 1382.7600000000002,
      "command": 2056.83
    },
    "gwallocation": {
      "domestic": {
        "poor_quality": 0.0,
        "total": 6653.51,
        "non_command": 6653.51,
        "command": 0.0
      },
      "total": {
        "poor_quality": 0.0,
        "total": 6653.51,
        "non_command": 6653.51,
        "command": 0.0
      },
      "industry": {
        "poor_quality": 0.0,
        "total": 0.0
      }
    },
    "stageOfExtraction": {
      "poor_quality": 0.0,
      "total": 75.98428176760731,
      "non_command": 86.14412600054996,
      "command": 0.0
    },
    "gwlevelData": null,
    "gwanalysisSeason": null,
    "gwtrendSlope": null,
    "waterTableRiseFall": null,
    "gwtrendAttention": null,
    "waterTableCategory": null,
    "message": null
  }
]